[
  {
    "img":"//y.gtimg.cn/music/photo_new/T002R90x90M000003RMaRI1iFoYd.jpg?max_age=2592000",
    "name":"告白气球",
    "length":"03:35",
    "remark":"周杰伦的床边故事",
    "singerName":"周杰伦",
    "url":"http://www.kugou.com/song/#hash=3C3D93A5615FB42486CAB22024945264&album_id=1645030"
  },
  {
    "img":"http://imge.kugou.com/stdmusic/20130524/20130524121442471308.jpg",
    "name":"唐人",
    "length":"03:47",
    "remark":"唐朝好男人 电视剧原声带",
    "singerName":"孙子涵",
    "url":"http://www.kugou.com/song/#hash=78EF301332B34FBAD3A7695F19EB6075&album_id=542933"
  },
  {
    "img":"http://imge.kugou.com/stdmusic/20170718/20170718190820946969.jpg",
    "name":"长安城外的夜",
    "length":"04:15",
    "remark":"长安城外的夜 专辑",
    "singerName":"孙子涵",
    "url":"http://www.kugou.com/song/#hash=6390088786431C7E988A9151DEDE3BE8&album_id=2859668"
  },
  {
    "img":"http://imge.kugou.com/stdmusic/20161010/20161010002343859583.jpg",
    "name":"回忆那么伤",
    "length":"03:56",
    "remark":"是最好的我",
    "singerName":"孙子涵",
    "url":"http://www.kugou.com/song/#hash=C716734C9FA87BA5A3CE895572232E6E&album_id=1793141"
  },
  {
    "img":"http://imge.kugou.com/stdmusic/20150718/20150718075812882235.jpg",
    "name":"全世界宣布爱你",
    "length":"03:55",
    "remark":"那时年少 原声大碟",
    "singerName":"孙子涵 李潇潇",
    "url":"http://www.kugou.com/song/#hash=B2333048169062AF18E7EF82A1D7E22F&album_id=885063"
  },
  {
    "img":"http://imge.kugou.com/stdmusic/20150719/20150719024805128915.jpg",
    "name":"爱的就是你",
    "length":"04:49",
    "remark":"唯一 专辑",
    "singerName":"王力宏",
    "url":"http://www.kugou.com/song/#hash=4BA7D60241818AAFDE62C0E7194229ED&album_id=967319"
  },
  {
    "img":"http://imge.kugou.com/stdmusic/20150719/20150719024805128915.jpg",
    "name":"爱的就是你",
    "length":"04:49",
    "remark":"唯一 专辑",
    "singerName":"王力宏",
    "url":"http://www.kugou.com/song/#hash=4BA7D60241818AAFDE62C0E7194229ED&album_id=967319"
  },
  {
    "img":"http://imge.kugou.com/stdmusic/20150719/20150719024805128915.jpg",
    "name":"爱的就是你",
    "length":"04:49",
    "remark":"唯一 专辑",
    "singerName":"王力宏",
    "url":"http://www.kugou.com/song/#hash=4BA7D60241818AAFDE62C0E7194229ED&album_id=967319"
  },
  {
    "img":"http://imge.kugou.com/stdmusic/20150719/20150719024805128915.jpg",
    "name":"爱的就是你",
    "length":"04:49",
    "remark":"唯一 专辑",
    "singerName":"王力宏",
    "url":"http://www.kugou.com/song/#hash=4BA7D60241818AAFDE62C0E7194229ED&album_id=967319"
  },
  {
    "img":"http://imge.kugou.com/stdmusic/20150719/20150719024805128915.jpg",
    "name":"爱的就是你",
    "length":"04:49",
    "remark":"唯一 专辑",
    "singerName":"王力宏",
    "url":"http://www.kugou.com/song/#hash=4BA7D60241818AAFDE62C0E7194229ED&album_id=967319"
  },
  {
    "img":"http://imge.kugou.com/stdmusic/20150719/20150719024805128915.jpg",
    "name":"爱的就是你",
    "length":"04:49",
    "remark":"唯一 专辑",
    "singerName":"王力宏",
    "url":"http://www.kugou.com/song/#hash=4BA7D60241818AAFDE62C0E7194229ED&album_id=967319"
  },
  {
    "img":"http://imge.kugou.com/stdmusic/20150719/20150719024805128915.jpg",
    "name":"爱的就是你",
    "length":"04:49",
    "remark":"唯一 专辑",
    "singerName":"王力宏",
    "url":"http://www.kugou.com/song/#hash=4BA7D60241818AAFDE62C0E7194229ED&album_id=967319"
  }

]